geoshapley/__init__.py
geoshapley/geoshapley.py
geoshapley-0.0.3.1.dist-info/METADATA
geoshapley-0.0.3.1.dist-info/WHEEL
geoshapley-0.0.3.1.dist-info/dependency_links.txt
geoshapley-0.0.3.1.dist-info/entry_points.txt
geoshapley-0.0.3.1.dist-info/top_level.txt
geoshapley-0.0.3.1.dist-info/RECORD
